tungl/__init__.py
tungl/tungl.py
tungl/LICENSE
tungl/cmake/FindTungl.cmake
tungl/include/tungl/api.h
tungl/include/tungl/c.h
tungl/include/tungl/colors.h
tungl/include/tungl/config.h
tungl/include/tungl/cxx.h
tungl/include/tungl/types.h
tungl/include/tungl/version.h
tungl/lib64/libtungl.so
tungl/lib64/libtungl.so.0
tungl/lib64/libtungl.so.0.1.4
tungl/src/tungl/tungl.cpp
tungl-0.1.4.post1.dist-info/METADATA
tungl-0.1.4.post1.dist-info/top_list.txt
tungl-0.1.4.post1.dist-info/WHEEL
tungl-0.1.4.post1.dist-info/RECORD
