Metadata-Version: 2.1
Name: tungl
Version: 0.1.4.post1
Requires-Python: >=3.6
Summary: Tungl
Author: Nicolas Weber
Author-email: nicolas.weber@neclab.eu
Classifier: License :: OSI Approved :: BSD License
Classifier: Programming Language :: Python :: 3 :: Only
Classifier: Programming Language :: C
Classifier: Programming Language :: C++
Download-URL: https://github.com/nec-research/tungl/tags
License: 3 BSD-License
Platform: linux_x86_x64
